spq/__init__.py
spq/base/__init__.py
spq/base/gr.py
spq/base/pq.py
spq/spq/__init__.py
spq/spq/aero.py
spq/spq/environ.py
spq/spq/pq-aero.json
spq-1.0.5.dist-info/licenses/LICENSE
spq-1.0.5.dist-info/METADATA
spq-1.0.5.dist-info/WHEEL
spq-1.0.5.dist-info/top_level.txt
spq-1.0.5.dist-info/RECORD
