Metadata-Version: 2.4
Name: spq
Version: 1.0.5
Summary: spq - simple physical quantities
Author-email: Hidden <ketakopter@gmail.com>
Project-URL: Homepage, https://github.com/ketakopter/spq
Classifier: Programming Language :: Python :: 3
Classifier: Operating System :: OS Independent
Classifier: License :: OSI Approved :: GNU General Public License (GPL)
Classifier: Topic :: Scientific/Engineering :: Physics
Classifier: Intended Audience :: Science/Research
Requires-Python: >=3.7
License-File: LICENSE
Requires-Dist: numpy
Dynamic: license-file
